ZYYA_Codes/__init__.py
ZYYA_Codes/Balance_Sheet/__init__.py
ZYYA_Codes/FOF_Analysis/Basic_Index.py
ZYYA_Codes/FOF_Analysis/__init__.py
ZYYA_Codes/Net_Value/__Net_Value_Analysis.py
ZYYA_Codes/Net_Value/__init__.py
ZYYA_Codes/Net_Value/api.py
ZYYA_Codes/Web_UI/Server.py
ZYYA_Codes/Web_UI/__init__.py
ZYYA_Codes/Web_UI/__pycache__/Server.cpython-312.pyc
ZYYA_Codes/Web_UI/__pycache__/__init__.cpython-312.pyc
ZYYA_Codes/Web_UI/templates/macro
ZYYA_Codes/Web_UI/templates/font/6xK3dSBYKcSV-LCoeQqfX1RYOo3qOK7g.ttf
ZYYA_Codes/Web_UI/templates/font/6xKydSBYKcSV-LCoeQqfX1RYOo3i54rwlxdr.ttf
ZYYA_Codes/Web_UI/templates/html/components.html
ZYYA_Codes/Web_UI/templates/html/demo.html
ZYYA_Codes/Web_UI/templates/html/fof.html
ZYYA_Codes/Web_UI/templates/html/fof_analysis.html
ZYYA_Codes/Web_UI/templates/html/fof_strategy_confirm.html
ZYYA_Codes/Web_UI/templates/html/home page.html
ZYYA_Codes/Web_UI/templates/html/login page.html
ZYYA_Codes/Web_UI/templates/html/login.html
ZYYA_Codes/Web_UI/templates/html/macro
ZYYA_Codes/Web_UI/templates/html/nb_components.html
ZYYA_Codes/Web_UI/templates/html/nb_jupyter_globe.html
ZYYA_Codes/Web_UI/templates/html/nb_jupyter_lab.html
ZYYA_Codes/Web_UI/templates/html/nb_jupyter_lab_tab.html
ZYYA_Codes/Web_UI/templates/html/nb_jupyter_notebook.html
ZYYA_Codes/Web_UI/templates/html/nb_jupyter_notebook_tab.html
ZYYA_Codes/Web_UI/templates/html/nb_nteract.html
ZYYA_Codes/Web_UI/templates/html/simple_chart.html
ZYYA_Codes/Web_UI/templates/html/simple_globe.html
ZYYA_Codes/Web_UI/templates/html/simple_page.html
ZYYA_Codes/Web_UI/templates/html/simple_tab.html
ZYYA_Codes/Web_UI/templates/html/snowball_console.html
ZYYA_Codes/Web_UI/templates/html/snowball_login.html
ZYYA_Codes/Web_UI/templates/html/snowball_welcome.html
ZYYA_Codes/Web_UI/templates/img/avatar04.png
ZYYA_Codes/Web_UI/templates/img/logo.png
ZYYA_Codes/Web_UI/templates/img/robot.gif
ZYYA_Codes/Web_UI/templates/js_code/all.min.79250b7051.css
ZYYA_Codes-2024.6.0.3.dist-info/LICENSE
ZYYA_Codes-2024.6.0.3.dist-info/METADATA
ZYYA_Codes-2024.6.0.3.dist-info/WHEEL
ZYYA_Codes-2024.6.0.3.dist-info/top_level.txt
ZYYA_Codes-2024.6.0.3.dist-info/RECORD
