Metadata-Version: 2.1
Name: ZYYA_Codes
Version: 2024.6.0.3
Summary: Python codes for China Post Yongan
Author: Yitong Gong
Author-email: yitong.gong@qq.com
License: MIT License
Requires-Python: >=3.7
License-File: LICENSE
Requires-Dist: pandas
Requires-Dist: numpy
Requires-Dist: chinese-calendar
Requires-Dist: chardet
Requires-Dist: pymongo
Requires-Dist: pyecharts
Requires-Dist: typing
Requires-Dist: pytz
Requires-Dist: imapclient
Requires-Dist: flask
